{
    "meta": {
        "name": "Space vim dark",
        "url": ""
    },
    "colors": {
        "terminal": {
            "background": "#262626",
            "foreground": "#a3a3a3",
            "cursor": "#a3a3a3",
            "color0": "#262626",
            "color1": "#cb4674",
            "color2": "#74d55c",
            "color3": "#a18417",
            "color4": "#627ad2",
            "color5": "#9f46b3",
            "color6": "#af87d7",
            "color7": "#a3a3a3",
            "color8": "#555f69",
            "color9": "#fc4474",
            "color10": "#96e931",
            "color11": "#e89e0f",
            "color12": "#4083cd",
            "color13": "#d358d5",
            "color14": "#22abbb",
            "color15": "#dfdfdf",
            "color16": "#fc4474",
            "color17": "#22abbb",
            "color18": "#96e931",
            "color19": "#e89e0f",
            "color20": "#4083cd",
            "color21": "#d358d5"
        }
    }
}
